seamm_datastore/__init__.py
seamm_datastore/_version.py
seamm_datastore/connect.py
seamm_datastore/flask_authorize_patch.py
seamm_datastore/util.py
seamm_datastore/data/sample_flowchart_v2.flow
seamm_datastore/data/Projects/sample_project1/Job_000092/final_structure.mmcif
seamm_datastore/data/Projects/sample_project1/Job_000092/flowchart.flow
seamm_datastore/data/Projects/sample_project1/Job_000092/job.out
seamm_datastore/data/Projects/sample_project1/Job_000092/job_data.json
seamm_datastore/data/Projects/sample_project1/Job_000092/references.db
seamm_datastore/data/Projects/sample_project1/Job_000092/seamm.db
seamm_datastore/data/Projects/sample_project1/Job_000092/1/step.out
seamm_datastore/data/Projects/sample_project1/Job_000092/2/band.out
seamm_datastore/data/Projects/sample_project1/Job_000092/2/charges.dat
seamm_datastore/data/Projects/sample_project1/Job_000092/2/detailed.out
seamm_datastore/data/Projects/sample_project1/Job_000092/2/dftb_in.hsd
seamm_datastore/data/Projects/sample_project1/Job_000092/2/dftb_pin.hsd
seamm_datastore/data/Projects/sample_project1/Job_000092/2/geom.out.gen
seamm_datastore/data/Projects/sample_project1/Job_000092/2/geom.out.xyz
seamm_datastore/data/Projects/sample_project1/Job_000092/2/results.tag
seamm_datastore/data/Projects/sample_project1/Job_000092/2/stdout.txt
seamm_datastore/data/Projects/sample_project1/Job_000092/2/step.out
seamm_datastore/data/Projects/sample_project1/Job_000093/final_structure.mmcif
seamm_datastore/data/Projects/sample_project1/Job_000093/flowchart.flow
seamm_datastore/data/Projects/sample_project1/Job_000093/job.out
seamm_datastore/data/Projects/sample_project1/Job_000093/job_data.json
seamm_datastore/data/Projects/sample_project1/Job_000093/references.db
seamm_datastore/data/Projects/sample_project1/Job_000093/seamm.db
seamm_datastore/data/Projects/sample_project1/Job_000093/1/step.out
seamm_datastore/data/Projects/sample_project1/Job_000093/2/band.out
seamm_datastore-2024.6.2.dist-info/LICENSE
seamm_datastore-2024.6.2.dist-info/METADATA
seamm_datastore-2024.6.2.dist-info/WHEEL
seamm_datastore-2024.6.2.dist-info/top_level.txt
seamm_datastore-2024.6.2.dist-info/RECORD
