Metadata-Version: 2.1
Name: seamm_datastore
Version: 2024.6.2
Summary: seamm_datastore
Home-page: https://github.com/molssi-seamm/seamm_datastore
Author: Jessica A. Nash (The Molecular Sciences Software Institute)
Author-email: janash@vt.edu
License: BSD-3-Clause
Keywords: SEAMM,datastore,dashboard
Platform: Linux
Platform: Mac OS-X
Platform: Unix
Classifier: Development Status :: 5 - Production/Stable
Classifier: Intended Audience :: Science/Research
Classifier: License :: OSI Approved :: BSD License
Classifier: Natural Language :: English
Classifier: Programming Language :: Python :: 3 :: Only
Classifier: Programming Language :: Python :: 3.8
Classifier: Programming Language :: Python :: 3.9
License-File: LICENSE
Requires-Dist: flask
Requires-Dist: flask-authorize
Requires-Dist: marshmallow
Requires-Dist: marshmallow-sqlalchemy
Requires-Dist: python-dateutil
Requires-Dist: six
Requires-Dist: sqlalchemy
Requires-Dist: werkzeug
